[{"route":"/"},{"route":"/blog"},{"route":"/blog/decordle-late-to-the-party","title":"Decordle, Late to the Party","description":"A deep dive into the word guessing game variant","published":true,"blurb":"I made a thing, but it is probably too late.","datePublished":"2023-05-29","slug":"decordle-late-to-the-party","authorImage":["../../../../assets/img/tristan.png"],"author":["Tristan Jesse"],"sourceFile":"decordle,-late-to-the-party.md"},{"route":"/blog/life-the-universe-and-everything","title":"Life, the Universe and Everything","description":"Catch up with my work life over the past couple years","published":true,"blurb":"Read along as I ramble about my current projects, feelings and what is coming next","datePublished":"2023-01-10","slug":"life-the-universe-and-everything","authorImage":["../../../../assets/img/tristan.png"],"author":["Tristan Jesse"],"sourceFile":"life-the-universe-and-everything.md"},{"route":"/tristygetsmaried"},{"route":"/tristygetsmaried/covid"}]